README.md
setup.py
qcc_product.egg-info/PKG-INFO
qcc_product.egg-info/SOURCES.txt
qcc_product.egg-info/dependency_links.txt
qcc_product.egg-info/top_level.txt
qccproduct/__init__.py
qccproduct/extra_passport.py
qccproduct/db/__init__.py
qccproduct/db/mongo.py
qccproduct/http_handler/__init__.py
qccproduct/http_handler/entrance_handler.py
qccproduct/http_handler/product_handler.py
qccproduct/model/__init__.py
qccproduct/model/product.py
qccproduct/routes/__init__.py
qccproduct/routes/product.py
qccproduct/service/__init__.py
qccproduct/service/ctrl_product.py
qccproduct/service/async_wrap/__init__.py
qccproduct/service/async_wrap/ctrl_product.py